pysubmit/__init__.py
pysubmit/command_line.py
pysubmit/template.py
pysubmit-1.0.1.dist-info/METADATA
pysubmit-1.0.1.dist-info/WHEEL
pysubmit-1.0.1.dist-info/entry_points.txt
pysubmit-1.0.1.dist-info/top_level.txt
pysubmit-1.0.1.dist-info/RECORD
