Metadata-Version: 2.1
Name: pysubmit
Version: 1.0.1
Summary: Versatile computation submission tool
Home-page: https://bitbucket.org/Mc_M/pysubmit
Author: Martin Lellep
Author-email: martin.lellep@gmail.com
License: MIT
Platform: UNKNOWN
Requires-Dist: jinja2
